zml/__init__.py
zml/backend.py
zml/context.py
zml/core.py
zml/crypt.py
zml/document.py
zml/exceptions.py
zml/lookup.py
zml/model.py
zml/node.py
zml/operator.py
zml/request.py
zml/resource.py
zml/semantic.py
zml/util.py
zml-0.10.13.dist-info/LICENSE
zml-0.10.13.dist-info/METADATA
zml-0.10.13.dist-info/WHEEL
zml-0.10.13.dist-info/top_level.txt
zml-0.10.13.dist-info/RECORD
