Metadata-Version: 2.1
Name: zml
Version: 0.10.13
Summary: zero markup language
Home-page: http://www.zml.org/
Author: Christof Hagedorn
Author-email: zeromage@neo.codes
License: UNKNOWN
Download-URL: https://pypi.python.org/pypi/zml
Keywords: zml,zero,markup,language,template,templating
Platform: UNKNOWN
Classifier: Programming Language :: Python
Classifier: Programming Language :: Python :: 3
Classifier: Programming Language :: Python :: 3.2
Classifier: Development Status :: 3 - Alpha
Classifier: Environment :: Web Environment
Classifier: Intended Audience :: Developers
Classifier: License :: OSI Approved :: BSD License
Classifier: Operating System :: OS Independent
Classifier: Topic :: Internet
Classifier: Topic :: Internet :: WWW/HTTP
Classifier: Topic :: Internet :: WWW/HTTP :: Dynamic Content
Classifier: Topic :: Internet :: WWW/HTTP :: WSGI
Classifier: Topic :: Software Development :: Libraries :: Python Modules
